Workbook

Sheet Data
A1: Month | B1: Units Sold | C1: Price per Unit | D1: Variable Cost per Unit | E1: Fixed Cost | F1: Marketing Cost
A2: Jan-2021 | B2: 500 | C2: 500 | D2: 220 | E2: 200000 | F2: 20000
A3: Feb-2021 | B3: 600 | C3: 500 | D3: 220 | E3: 200000 | F3: 25000
A4: Mar-2021 | B4: 700 | C4: 500 | D4: 220 | E4: 200000 | F4: 30000
A5: Apr-2021 | B5: 800 | C5: 500 | D5: 220 | E5: 200000 | F5: 35000
A6: May-2021 | B6: 900 | C6: 500 | D6: 220 | E6: 200000 | F6: 40000
A7: Jun-2021 | B7: 1000 | C7: 500 | D7: 220 | E7: 200000 | F7: 45000
A8: Jul-2021 | B8: 1100 | C8: 500 | D8: 220 | E8: 200000 | F8: 50000
A9: Aug-2021 | B9: 1200 | C9: 500 | D9: 220 | E9: 200000 | F9: 55000
A10: Sep-2021 | B10: 1300 | C10: 500 | D10: 220 | E10: 200000 | F10: 60000
A11: Oct-2021 | B11: 1400 | C11: 500 | D11: 220 | E11: 200000 | F11: 65000
A12: Nov-2021 | B12: 1500 | C12: 500 | D12: 220 | E12: 200000 | F12: 70000
A13: Dec-2021 | B13: 1600 | C13: 500 | D13: 220 | E13: 200000 | F13: 75000
... A49: Dec-2024 | B49: 2000 | C49: 560 | D49: 250 | E49: 230000 | F49: 90000

Sheet Calculation
A1: Month | B1: Revenue | C1: Total Variable Cost | D1: Total Cost | E1: Profit | H1: Break -Even Units
A2: =Data!A2 -> Jan-2021 | B2: =Data!B2 * Data!C2 -> 250000 | C2: =Data!B2 * Data!D2 -> 110000 | D2: =C2 + Data!E2 + Data!F2 -> 330000 | E2: =B2 - D2 -> -80000 | H2: =Data!E2 / (Data!C2 - Data!D2) -> 714.28571
A3: =Data!A3 -> Feb-2021 | B3: =Data!B3 * Data!C3 -> 300000 | C3: =Data!B3 * Data!D3 -> 132000 | D3: =C3 + Data!E3 + Data!F3 -> 357000 | E3: =B3 - D3 -> -57000
A4: =Data!A4 -> Mar-2021 | B4: =Data!B4 * Data!C4 -> 350000 | C4: =Data!B4 * Data!D4 -> 154000 | D4: =C4 + Data!E4 + Data!F4 -> 384000 | E4: =B4 - D4 -> -34000
A5: =Data!A5 -> Apr-2021 | B5: =Data!B5 * Data!C5 -> 400000 | C5: =Data!B5 * Data!D5 -> 176000 | D5: =C5 + Data!E5 + Data!F5 -> 411000 | E5: =B5 - D5 -> -11000
A6: =Data!A6 -> May-2021 | B6: =Data!B6 * Data!C6 -> 450000 | C6: =Data!B6 * Data!D6 -> 198000 | D6: =C6 + Data!E6 + Data!F6 -> 438000 | E6: =B6 - D6 -> 12000
A7: =Data!A7 -> Jun-2021 | B7: =Data!B7 * Data!C7 -> 500000 | C7: =Data!B7 * Data!D7 -> 220000 | D7: =C7 + Data!E7 + Data!F7 -> 465000 | E7: =B7 - D7 -> 35000
A8: =Data!A8 -> Jul-2021 | B8: =Data!B8 * Data!C8 -> 550000 | C8: =Data!B8 * Data!D8 -> 242000 | D8: =C8 + Data!E8 + Data!F8 -> 492000 | E8: =B8 - D8 -> 58000
A9: =Data!A9 -> Aug-2021 | B9: =Data!B9 * Data!C9 -> 600000 | C9: =Data!B9 * Data!D9 -> 264000 | D9: =C9 + Data!E9 + Data!F9 -> 519000 | E9: =B9 - D9 -> 81000
A10: =Data!A10 -> Sep-2021 | B10: =Data!B10 * Data!C10 -> 650000 | C10: =Data!B10 * Data!D10 -> 286000 | D10: =C10 + Data!E10 + Data!F10 -> 546000 | E10: =B10 - D10 -> 104000
A11: =Data!A11 -> Oct-2021 | B11: =Data!B11 * Data!C11 -> 700000 | C11: =Data!B11 * Data!D11 -> 308000 | D11: =C11 + Data!E11 + Data!F11 -> 573000 | E11: =B11 - D11 -> 127000
A12: =Data!A12 -> Nov-2021 | B12: =Data!B12 * Data!C12 -> 750000 | C12: =Data!B12 * Data!D12 -> 330000 | D12: =C12 + Data!E12 + Data!F12 -> 600000 | E12: =B12 - D12 -> 150000
A13: =Data!A13 -> Dec-2021 | B13: =Data!B13 * Data!C13 -> 800000 | C13: =Data!B13 * Data!D13 -> 352000 | D13: =C13 + Data!E13 + Data!F13 -> 627000 | E13: =B13 - D13 -> 173000
A14: =Data!A14 -> Jan-2022 | B14: =Data!B14 * Data!C14 -> 312000 | C14: =Data!B14 * Data!D14 -> 138000 | D14: =C14 + Data!E14 + Data!F14 -> 370000 | E14: =B14 - D14 -> -58000
... A49: =Data!A49 -> Dec-2024 | B49: =Data!B49 * Data!C49 -> 1120000 | C49: =Data!B49 * Data!D49 -> 500000 | D49: =C49 + Data!E49 + Data!F49 -> 820000 | E49: =B49 - D49 -> 300000

Sheet Dashboard
A1: Financial Modeling Dashboard Retail Business Performance Analysis (2021–2024)
B4: Total Revenue | D4: Total Profit | F4: Break-Even Value | H4: Payback Period
B5: =SUM(Calculation!B2:B49) -> 30704000 | D5: =SUM(Calculation!E2:E49) -> 4340000 | F5: =Calculation!H2 -> 714.28571 | G5: Units | H5: 2 Months
A7: Revenue | G7: Profit Analysis | J7: Scenario Manager
J9: Scenario | K9: Units | L9: Price | M9: Cost | N9: Fixed Cost | O9: Marketing | P9: Profit
J10: Best | K10: 1800 | L10: 580 | M10: 200 | N10: 200000 | O10: 70000 | P10: =(K10*L10)-(K10*M10+N10+O10) -> 414000
J11: Normal | K11: 1300 | L11: 540 | M11: 240 | N11: 220000 | O11: 50000 | P11: =(K11*L11)-(K11*M11+N11+O11) -> 120000
J12: Worst | K12: 900 | L12: 480 | M12: 280 | N12: 230000 | O12: 40000 | P12: =(K12*L12)-(K12*M12+N12+O12) -> -90000
L21: Key Insights
L23: • Profit increases significantly after crossing the break-even point (~714 units).
L24: • Selling price has the highest positive impact on profitability.
L25: • Variable cost strongly affects profit margins—cost control is critical.
A26: Financial breakdown | G26: Waterfall Chart | L26: • Higher marketing spend is associated with increased sales and revenue growth.
L27: • Business performance improves consistently over the years, showing a positive growth trend.
L28: • Cost structure (fixed + variable) is the primary reason for negative profitability.
L30: Business Recommendations
L32: • Focus on increasing sales volume through targeted marketing strategies.
L33: • Optimize pricing strategy to maximize revenue without reducing demand.
L34: • Control variable costs through better supplier negotiation and efficiency.
L35: • Maintain sales above the break-even level to ensure profitability.
L36: • Continuously monitor financial performance for better decision-making.
N49: Prepared by: Muskan Yadav
N50: Tools Used: Excel | Financial Modeling | Data Analysis

Sheet Sheet11
A3: Row Labels | B3: Sum of Revenue | C3: Sum of Total Cost
A4: Apr-2021 | B4: 400000 | C4: 411000
A5: Apr-2022 | B5: 468000 | C5: 451000
A6: Apr-2023 | B6: 540000 | C6: 500000
A7: Apr-2024 | B7: 616000 | C7: 550000
A8: Aug-2021 | B8: 600000 | C8: 519000
A9: Aug-2022 | B9: 676000 | C9: 559000
A10: Aug-2023 | B10: 756000 | C10: 616000
A11: Aug-2024 | B11: 840000 | C11: 670000
A12: Dec-2021 | B12: 800000 | C12: 627000
A13: Dec-2022 | B13: 884000 | C13: 667000
A14: Dec-2023 | B14: 972000 | C14: 732000
A15: Dec-2024 | B15: 1120000 | C15: 820000
... A52: Grand Total | B52: 30704000 | C52: 26364000

Sheet Sheet12
A3: Row Labels | B3: Sum of Profit
A4: Apr-2021 | B4: -11000
A5: Apr-2022 | B5: 17000
A6: Apr-2023 | B6: 40000
A7: Apr-2024 | B7: 66000
A8: Aug-2021 | B8: 81000
A9: Aug-2022 | B9: 117000
A10: Aug-2023 | B10: 140000
A11: Aug-2024 | B11: 170000
A12: Dec-2021 | B12: 173000
A13: Dec-2022 | B13: 217000
A14: Dec-2023 | B14: 240000
A15: Dec-2024 | B15: 300000
... A52: Grand Total | B52: 4340000

Sheet Sheet14
A1: Units | B1: Revenue | C1: Total cost | K1: Component | L1: Values
A2: 0 | B2: =A2*500 -> 0 | C2: =200000+(Sheet14!A2*220) -> 200000 | K2: Revenue | L2: 500000
A3: 200 | B3: =A3*500 -> 100000 | C3: =200000+(Sheet14!A3*220) -> 244000 | K3: Variable Cost | L3: -200000
A4: 400 | B4: =A4*500 -> 200000 | C4: =200000+(Sheet14!A4*220) -> 288000 | K4: Fixed Cost | L4: -200000
A5: 600 | B5: =A5*500 -> 300000 | C5: =200000+(Sheet14!A5*220) -> 332000 | K5: Marketing Cost | L5: -50000
A6: 800 | B6: =A6*500 -> 400000 | C6: =200000+(Sheet14!A6*220) -> 376000 | K6: Profit | L6: 50000
A7: 1000 | B7: =A7*500 -> 500000 | C7: =200000+(Sheet14!A7*220) -> 420000
